wtfml/__init__.py
wtfml/data_loaders/__init__.py
wtfml/data_loaders/image/__init__.py
wtfml/data_loaders/image/classification.py
wtfml/data_loaders/image/loader.py
wtfml/data_loaders/image/segmentation.py
wtfml/data_loaders/nlp/__init__.py
wtfml/data_loaders/tabular/__init__.py
wtfml/engine/__init__.py
wtfml/engine/engine.py
wtfml/engine/rcnn_engine.py
wtfml/logger/__init__.py
wtfml/logger/logger.py
wtfml/utils/__init__.py
wtfml/utils/average_meter.py
wtfml/utils/early_stopping.py
wtfml-0.0.3.dist-info/LICENSE
wtfml-0.0.3.dist-info/METADATA
wtfml-0.0.3.dist-info/WHEEL
wtfml-0.0.3.dist-info/top_level.txt
wtfml-0.0.3.dist-info/RECORD
