Metadata-Version: 2.1
Name: wtfml
Version: 0.0.3
Summary: WTFML: Well That's Fantastic Machine Learning
Home-page: https://github.com/abhishekkrthakur/wtfml
Author: Abhishek Thakur
Author-email: abhishek4@gmail.com
License: MIT License
Platform: linux
Platform: unix
Requires-Python: >3.5.2
Requires-Dist: scikit-learn (>=0.22.1)
